inspyred/__init__.py
inspyred/benchmarks.py
inspyred/cli.py
inspyred/ec/__init__.py
inspyred/ec/analysis.py
inspyred/ec/archivers.py
inspyred/ec/ec.py
inspyred/ec/emo.py
inspyred/ec/evaluators.py
inspyred/ec/generators.py
inspyred/ec/migrators.py
inspyred/ec/observers.py
inspyred/ec/replacers.py
inspyred/ec/selectors.py
inspyred/ec/terminators.py
inspyred/ec/utilities.py
inspyred/ec/variators/__init__.py
inspyred/ec/variators/crossovers.py
inspyred/ec/variators/mutators.py
inspyred/ec/variators/variators.py
inspyred/swarm/__init__.py
inspyred/swarm/swarm.py
inspyred/swarm/topologies.py
inspyred-1.0.3.dist-info/AUTHORS.rst
inspyred-1.0.3.dist-info/LICENSE
inspyred-1.0.3.dist-info/METADATA
inspyred-1.0.3.dist-info/WHEEL
inspyred-1.0.3.dist-info/entry_points.txt
inspyred-1.0.3.dist-info/top_level.txt
inspyred-1.0.3.dist-info/RECORD
