Metadata-Version: 2.1
Name: inspyred
Version: 1.0.3
Summary: A framework for creating bio-inspired computational intelligence algorithms in Python
Home-page: https://github.com/aarongarrett/inspyred
Author: Aaron Garrett
Author-email: garrett@inspiredintelligence.io
License: MIT
Classifier: Development Status :: 5 - Production/Stable
Classifier: Intended Audience :: Science/Research
Classifier: License :: OSI Approved :: MIT License
Classifier: Natural Language :: English
Classifier: Operating System :: OS Independent
Classifier: Programming Language :: Python :: 3.8
Classifier: Programming Language :: Python :: 3.9
Classifier: Programming Language :: Python :: 3.10
Classifier: Programming Language :: Python :: 3.11
Classifier: Programming Language :: Python :: 3.12
Classifier: Programming Language :: Python :: 3.13
Classifier: Topic :: Scientific/Engineering :: Artificial Intelligence
License-File: LICENSE
License-File: AUTHORS.rst
Requires-Dist: Click>=6.0
Requires-Dist: numpy
Provides-Extra: all
Requires-Dist: ppft[dill]; extra == "all"
Requires-Dist: matplotlib; extra == "all"
Provides-Extra: doc
Requires-Dist: Sphinx; extra == "doc"
Provides-Extra: dev
Requires-Dist: inspyred[all]; extra == "dev"
Requires-Dist: inspyred[doc]; extra == "dev"
Requires-Dist: wheel; extra == "dev"
Requires-Dist: flake8; extra == "dev"
Requires-Dist: tox; extra == "dev"
Requires-Dist: coverage; extra == "dev"
Requires-Dist: pytest; extra == "dev"
